pydantic_swift_code/__init__.py
pydantic_swift_code/main.py
pydantic_swift_code-0.2.0.dist-info/LICENSE
pydantic_swift_code-0.2.0.dist-info/METADATA
pydantic_swift_code-0.2.0.dist-info/WHEEL
pydantic_swift_code-0.2.0.dist-info/RECORD
