Metadata-Version: 2.1
Name: pydantic-swift-code
Version: 0.2.0
Summary: pydantic SWIFT/BIC code type
Author: Artem Kuchumov
Author-email: duketemon@gmail.com
Requires-Python: >=3.9,<4.0
Classifier: Programming Language :: Python :: 3
Classifier: Programming Language :: Python :: 3.9
Classifier: Programming Language :: Python :: 3.10
Classifier: Programming Language :: Python :: 3.11
Classifier: Programming Language :: Python :: 3.12
Classifier: Programming Language :: Python :: 3.13
Requires-Dist: pydantic (==2.10.1)
